certification/__init__.py
certification/certificate_generator.py
course_certification-1.1.0.dist-info/LICENSE.txt
course_certification-1.1.0.dist-info/METADATA
course_certification-1.1.0.dist-info/WHEEL
course_certification-1.1.0.dist-info/entry_points.txt
course_certification-1.1.0.dist-info/top_level.txt
course_certification-1.1.0.dist-info/RECORD
