Metadata-Version: 2.1
Name: course-certification
Version: 1.1.0
Summary: Generate course certificates from Google Spreadsheets
Home-page: https://github.com/karthikpawar/certification
Author: CloudxLab
Author-email: karthik@cloudxlab.com
License: MIT
Keywords: Certificate generation
Platform: UNKNOWN
Classifier: Programming Language :: Python :: 3.4
Classifier: Programming Language :: Python :: 3.5
Classifier: Programming Language :: Python :: 3.6
Classifier: License :: OSI Approved :: MIT License
Requires-Dist: imgkit (==0.1.8)
Requires-Dist: pystache (==0.5.4)
Requires-Dist: gspread (==0.6.2)
Requires-Dist: pdfkit
Requires-Dist: google-auth-oauthlib (==0.2.0)
Requires-Dist: oauth2client (==4.0.0)
Requires-Dist: oauthlib (==3.0.1)
Requires-Dist: requests-oauthlib (==1.2.0)
